bite_grads/__init__.py
bite_grads/ctl.py
bite_grads/grads.py
bite_grads/tools.py
bite_grads-0.0.1.dist-info/LICENSE
bite_grads-0.0.1.dist-info/METADATA
bite_grads-0.0.1.dist-info/WHEEL
bite_grads-0.0.1.dist-info/top_level.txt
bite_grads-0.0.1.dist-info/RECORD
