Metadata-Version: 2.1
Name: bite-grads
Version: 0.0.1
Summary: For reading GrADS format data.
Home-page: https://github.com/Mo-Dabao/BiteGrADS
Author: modabao
Author-email: mo_dabao@qq.com
Classifier: License :: OSI Approved :: GNU Affero General Public License v3
Requires-Python: >=3.5
License-File: LICENSE
Requires-Dist: xarray
Requires-Dist: dask
Requires-Dist: pyproj
Requires-Dist: numpy
Requires-Dist: pandas
